geonetworkx/__init__.py
geonetworkx/generators.py
geonetworkx/geodigraph.py
geonetworkx/geograph.py
geonetworkx/geometry_operations.py
geonetworkx/geomultidigraph.py
geonetworkx/geomultigraph.py
geonetworkx/readwrite.py
geonetworkx/settings.py
geonetworkx/simplify.py
geonetworkx/examples/geograph_merge.py
geonetworkx/examples/isochrones.py
geonetworkx/examples/spatial_points_merge.py
geonetworkx/testing/__init__.py
geonetworkx/testing/utils.py
geonetworkx/tests/__init__.py
geonetworkx/tests/test_classes.py
geonetworkx/tests/test_geometry_operations.py
geonetworkx/tests/test_readwrite.py
geonetworkx/tests/test_simplify.py
geonetworkx/tests/test_tools.py
geonetworkx/tests/test_utils.py
geonetworkx/tests/datasets/__init__.py
geonetworkx/tests/datasets/copenhagen_buildings.geojson
geonetworkx/tests/datasets/copenhagen_ferry_net_edges.geojson
geonetworkx/tests/datasets/copenhagen_ferry_net_nodes.geojson
geonetworkx/tests/datasets/copenhagen_streets_net_edges.geojson
geonetworkx/tests/datasets/copenhagen_streets_net_nodes.geojson
geonetworkx/tests/datasets/grenoble_isere_edges.geojson
geonetworkx/tests/datasets/grenoble_isere_nodes.geojson
geonetworkx/tests/datasets/grenoble_streets_200_edges.geojson
geonetworkx/tests/datasets/grenoble_streets_200_nodes.geojson
geonetworkx/tests/datasets/grenoble_streets_500_edges.geojson
geonetworkx/tests/datasets/grenoble_streets_500_nodes.geojson
geonetworkx/tests/datasets/import_datasets.py
geonetworkx/tools/__init__.py
geonetworkx/tools/isochrones.py
geonetworkx/tools/spatial_merge.py
geonetworkx/utils/__init__.py
geonetworkx/utils/geograph_utils.py
geonetworkx/utils/voronoi_utils.py
geonetworkx-0.5.3.dist-info/LICENCE
geonetworkx-0.5.3.dist-info/METADATA
geonetworkx-0.5.3.dist-info/WHEEL
geonetworkx-0.5.3.dist-info/top_level.txt
geonetworkx-0.5.3.dist-info/RECORD
