Metadata-Version: 2.1
Name: geonetworkx
Version: 0.5.3
Summary: Python tools for geographic graphs
Home-page: UNKNOWN
Author: Hugo Chareyre - Artelys
Author-email: hugo.chareyre@artelys.com
License: UNKNOWN
Platform: UNKNOWN
Classifier: Programming Language :: Python :: 3
Classifier: Operating System :: OS Independent
Requires-Dist: pyproj (>=2.2)
Requires-Dist: geopy (>=1.12.0)
Requires-Dist: geopandas (>=0.7)
Requires-Dist: networkx (>=2.3)
Requires-Dist: numpy (>=1.12.0)
Requires-Dist: pandas (>=0.25.0)
Requires-Dist: shapely (>=1.2.18)
Requires-Dist: scipy (>=0.19.0rc2)
Requires-Dist: nose (>=1.3.7)
